litezip/__init__.py
litezip/_version.py
litezip/completezip.py
litezip/exceptions.py
litezip/logger.py
litezip/main.py
litezip/validate.py
litezip/cli/__init__.py
litezip/cli/common.py
litezip/cli/completezip2litezip.py
litezip/cli/validate.py
litezip/contrib/__init__.py
litezip/contrib/pytest/__init__.py
litezip/contrib/pytest/data/completezip/collection.xml
litezip/contrib/pytest/data/completezip/m37154/index.cnxml
litezip/contrib/pytest/data/completezip/m37154/index.cnxml.html
litezip/contrib/pytest/data/completezip/m37154/index_auto_generated.cnxml
litezip/contrib/pytest/data/completezip/m37217/Lab4 Fill Order.png
litezip/contrib/pytest/data/completezip/m37217/MSP430 Interrupt Execution.png
litezip/contrib/pytest/data/completezip/m37217/index.cnxml
litezip/contrib/pytest/data/completezip/m37217/index.cnxml.html
litezip/contrib/pytest/data/completezip/m37217/index_auto_generated.cnxml
litezip/contrib/pytest/data/completezip/m37386/MSP430 ADC10CTL0.png
litezip/contrib/pytest/data/completezip/m37386/MSP430 ADC10CTL1.png
litezip/contrib/pytest/data/completezip/m37386/index.cnxml
litezip/contrib/pytest/data/completezip/m37386/index.cnxml.html
litezip/contrib/pytest/data/completezip/m37386/index_auto_generated.cnxml
litezip/contrib/pytest/data/completezip/m40645/Lab4 Fill Order.png
litezip/contrib/pytest/data/completezip/m40645/index.cnxml
litezip/contrib/pytest/data/completezip/m40645/index.cnxml.html
litezip/contrib/pytest/data/completezip/m40645/index_auto_generated.cnxml
litezip/contrib/pytest/data/completezip/m40646/Photodiode.png
litezip/contrib/pytest/data/completezip/m40646/index.cnxml
litezip/contrib/pytest/data/completezip/m40646/index.cnxml.html
litezip/contrib/pytest/data/completezip/m40646/index_auto_generated.cnxml
litezip/contrib/pytest/data/completezip/m42303/index.cnxml
litezip/contrib/pytest/data/completezip/m42303/index.cnxml.html
litezip/contrib/pytest/data/completezip/m42303/index_auto_generated.cnxml
cnx_litezip-1.6.0.dist-info/LICENSE.txt
cnx_litezip-1.6.0.dist-info/METADATA
cnx_litezip-1.6.0.dist-info/WHEEL
cnx_litezip-1.6.0.dist-info/entry_points.txt
cnx_litezip-1.6.0.dist-info/top_level.txt
cnx_litezip-1.6.0.dist-info/RECORD
