Metadata-Version: 2.1
Name: cnx-litezip
Version: 1.6.0
Summary: Connexions LiteZip Library
Home-page: https://github.com/connexions/cnx-litezip
Author: Connexions team
Author-email: info@cnx.org
License: LGPL, See also LICENSE.txt
Platform: UNKNOWN
Requires-Dist: cnxml
Requires-Dist: lxml
Requires-Dist: python-magic
Provides-Extra: test
Requires-Dist: pytest; extra == 'test'
Requires-Dist: pytest-cov; extra == 'test'
Requires-Dist: pytest-runner; extra == 'test'
